{"State.fe9d88b4-6cd0-4d43-aa42-5a5993bc9da7": {"id": "ffe0d1d6-268d-443d-95ce-643c9c2de867", "created_at": "2024-05-05T05:48:36.212452", "updated_at": "2024-05-05T05:48:36.212464", "name": "California", "__class__": "State"}, "State.e1c7c2a6-717f-4597-83c7-b609598a58dd": {"id": "93c915de-a27f-4d5b-ba9f-232678bbc214", "created_at": "2024-05-05T05:48:36.212508", "updated_at": "2024-05-05T05:48:36.212512", "name": "Arizona", "__class__": "State"}, "Place.1dfee12a-9341-4087-9ad0-4e2fdc5d9022": {"id": "3b0274d5-5740-4897-b91e-c7135e9a3899", "created_at": "2024-05-05T05:48:36.212573", "updated_at": "2024-05-05T05:48:36.212578", "city_id": 1, "user_id": 1, "name": "My little house", "number_rooms": 4, "number_bathrooms": 2, "max_guest": 10, "price_by_night": 300, "latitude": 37.773972, "longitude": -122.431297, "__class__": "Place"}, "State.d86581fb-41d2-4485-b852-8db8fb3d01ca": {"id": "3c75a511-8aff-42ad-940b-3bb3cb487370", "created_at": "2024-05-05T05:48:36.212618", "updated_at": "2024-05-05T05:48:36.212623", "name": "California", "__class__": "State"}, "State.d4d765f9-2c88-4f2c-8acb-392fa8f658d7": {"id": "132f6308-3b1c-48dd-a7e5-bff854027164", "created_at": "2024-05-05T05:48:36.212660", "updated_at": "2024-05-05T05:48:36.212665", "name": "Arizona", "__class__": "State"}, "Place.2dc40669-fc66-4653-b721-adb264de255c": {"id": "95a6fbe9-b54b-43a2-91a4-4db68e66407f", "created_at": "2024-05-05T05:48:36.212710", "updated_at": "2024-05-05T05:48:36.212715", "city_id": 1, "user_id": 1, "name": "My little house", "number_rooms": 4, "number_bathrooms": 2, "max_guest": 10, "price_by_night": 300, "latitude": 37.773972, "longitude": -122.431297, "__class__": "Place"}, "State.edd1052b-d605-4890-8a68-8ae075530e9a": {"id": "b269654b-a64e-40c9-a5b0-620803837420", "created_at": "2024-05-05T05:48:36.212755", "updated_at": "2024-05-05T05:48:36.212759", "name": "California", "__class__": "State"}, "State.3ee73fb5-c453-44e3-8776-59c6c152ab0e": {"id": "356e0dab-3361-47ca-90a3-9a1aaa5aa460", "created_at": "2024-05-05T05:48:36.212794", "updated_at": "2024-05-05T05:48:36.212798", "name": "Arizona", "__class__": "State"}, "Place.a18509f9-e4a2-4107-882b-88983df6d739": {"id": "767247b8-a616-4254-aeec-5271f210c41b", "created_at": "2024-05-05T05:48:36.212840", "updated_at": "2024-05-05T05:48:36.212844", "city_id": 1, "user_id": 1, "name": "My little house", "number_rooms": 4, "number_bathrooms": 2, "max_guest": 10, "price_by_night": 300, "latitude": 37.773972, "longitude": -122.431297, "__class__": "Place"}, "State.7a74fd0e-9d3a-4aa2-81b1-577be275cea0": {"id": "fe338434-f7fd-4423-b5fb-6eaf4c1164d2", "created_at": "2024-05-05T05:48:36.212880", "updated_at": "2024-05-05T05:48:36.212884", "name": "California", "__class__": "State"}, "State.794d3a85-13dd-4e8d-bb48-880517571cbf": {"id": "4618c037-2b9e-4918-8f5e-ca95ae007376", "created_at": "2024-05-05T05:48:36.212918", "updated_at": "2024-05-05T05:48:36.212922", "name": "Arizona", "__class__": "State"}, "Place.05945443-9618-461b-b124-ed537187ec16": {"id": "63d8ee42-b658-4a0f-aa0e-e96fb321c876", "created_at": "2024-05-05T05:48:36.212960", "updated_at": "2024-05-05T05:48:36.212965", "city_id": 1, "user_id": 1, "name": "My little house", "number_rooms": 4, "number_bathrooms": 2, "max_guest": 10, "price_by_night": 300, "latitude": 37.773972, "longitude": -122.431297, "__class__": "Place"}, "State.60f72db4-03bd-4d42-9af2-28a370c7e98e": {"id": "e5185e77-7a04-40ab-9efc-18f81bff50d3", "created_at": "2024-05-05T05:48:36.213001", "updated_at": "2024-05-05T05:48:36.213006", "name": "California", "__class__": "State"}, "State.21f2754b-cfdf-4c61-a735-1073363d862b": {"id": "a67c1dbf-2dc5-4b01-a5cf-32e4ac97a52c", "created_at": "2024-05-05T05:48:36.213039", "updated_at": "2024-05-05T05:48:36.213043", "name": "Arizona", "__class__": "State"}, "Place.753064b7-cbbb-47c7-84f8-1ef4ce63bca4": {"id": "96fd1ed7-2ecc-4de3-be9e-f96d3637e060", "created_at": "2024-05-05T05:48:36.213080", "updated_at": "2024-05-05T05:48:36.213084", "city_id": 1, "user_id": 1, "name": "My little house", "number_rooms": 4, "number_bathrooms": 2, "max_guest": 10, "price_by_night": 300, "latitude": 37.773972, "longitude": -122.431297, "__class__": "Place"}, "State.e3c4e004-63b4-4157-84bb-0e3ecf8e0a5b": {"id": "25af9e60-8f9c-49fb-a52f-335f2a820a1d", "created_at": "2024-05-05T05:48:36.213124", "updated_at": "2024-05-05T05:48:36.213129", "name": "California", "__class__": "State"}, "State.4646d430-a4ba-45e1-b142-a0f5d160bcb7": {"id": "e8f937e0-7198-4191-a536-385e3264947c", "created_at": "2024-05-05T05:48:36.213162", "updated_at": "2024-05-05T05:48:36.213167", "name": "Arizona", "__class__": "State"}, "Place.a6c6d5b8-1a67-4154-9894-cf60ab9e00f7": {"id": "2567d5d0-4d08-48f9-843c-a907589f25c4", "created_at": "2024-05-05T05:48:36.213204", "updated_at": "2024-05-05T05:48:36.213208", "city_id": 1, "user_id": 1, "name": "My little house", "number_rooms": 4, "number_bathrooms": 2, "max_guest": 10, "price_by_night": 300, "latitude": 37.773972, "longitude": -122.431297, "__class__": "Place"}, "State.8a4ac6b1-4c56-460d-b79e-e8558895e86a": {"id": "8a4ac6b1-4c56-460d-b79e-e8558895e86a", "created_at": "2024-05-05T05:48:36.219827", "updated_at": "2024-05-05T05:48:36.219861", "name": "California", "__class__": "State"}, "State.0f20abe6-625b-439a-be33-fac40131127d": {"id": "0f20abe6-625b-439a-be33-fac40131127d", "created_at": "2024-05-05T05:48:36.220582", "updated_at": "2024-05-05T05:48:36.220610", "name": "Arizona", "__class__": "State"}, "Place.f0ad6244-2183-478a-80f9-749cf607e13f": {"id": "f0ad6244-2183-478a-80f9-749cf607e13f", "created_at": "2024-05-05T05:48:36.221386", "updated_at": "2024-05-05T05:48:36.221429", "city_id": 1, "user_id": 1, "name": "My little house", "number_rooms": 4, "number_bathrooms": 2, "max_guest": 10, "price_by_night": 300, "latitude": 37.773972, "longitude": -122.431297, "__class__": "Place"}}